pytest_bg_process/__init__.py
pytest_bg_process/plugin.py
pytest_bg_process-0.0.3.dist-info/LICENSE
pytest_bg_process-0.0.3.dist-info/METADATA
pytest_bg_process-0.0.3.dist-info/WHEEL
pytest_bg_process-0.0.3.dist-info/entry_points.txt
pytest_bg_process-0.0.3.dist-info/top_level.txt
pytest_bg_process-0.0.3.dist-info/RECORD
