Metadata-Version: 2.1
Name: pytest-bg-process
Version: 0.0.3
Summary: Pytest plugin to initialize background process
Home-page: https://github.com/IndlgO/pytest-bg-process
Author: NoThlnG
Author-email: hanguyl91@gmail.com
Maintainer: NoThlnG
Maintainer-email: hanguyl91@gmail.com
License: MIT
Platform: UNKNOWN
Classifier: Development Status :: 4 - Beta
Classifier: Framework :: Pytest
Classifier: Intended Audience :: Developers
Classifier: Topic :: Software Development :: Testing
Classifier: Programming Language :: Python
Classifier: Programming Language :: Python :: 3
Classifier: Programming Language :: Python :: 3.5
Classifier: Programming Language :: Python :: 3.6
Classifier: Programming Language :: Python :: 3.7
Classifier: Programming Language :: Python :: 3.8
Classifier: Programming Language :: Python :: 3 :: Only
Classifier: Programming Language :: Python :: Implementation :: CPython
Classifier: Programming Language :: Python :: Implementation :: PyPy
Classifier: Operating System :: OS Independent
Classifier: License :: OSI Approved :: MIT License
Requires-Python: >=3.5
License-File: LICENSE
Requires-Dist: pytest (>=3.5.0)
